LICENSE
MANIFEST.in
README.rst
buildout.cfg
develop.cfg
requirements.txt
setup.py
version.txt
bob/__init__.py
bob.db.fv3d.egg-info/PKG-INFO
bob.db.fv3d.egg-info/SOURCES.txt
bob.db.fv3d.egg-info/dependency_links.txt
bob.db.fv3d.egg-info/entry_points.txt
bob.db.fv3d.egg-info/not-zip-safe
bob.db.fv3d.egg-info/requires.txt
bob.db.fv3d.egg-info/top_level.txt
bob/db/__init__.py
bob/db/fv3d/__init__.py
bob/db/fv3d/create.py
bob/db/fv3d/driver.py
bob/db/fv3d/files.txt
bob/db/fv3d/models.py
bob/db/fv3d/query.py
bob/db/fv3d/test.py
doc/conf.py
doc/guide.rst
doc/index.rst
doc/py_api.rst