Metadata-Version: 1.1
Name: bob.db.fv3d
Version: 1.1.1
Summary: 3D Fingervein Database Access API for Bob
Home-page: https://gitlab.idiap.ch/bob/bob.db.fv3d
Author: Andre Anjos
Author-email: andre.anjos@idiap.ch
License: BSD
Keywords: fingervein recognition,bob,bob.db,VERA,Fingervein
Platform: UNKNOWN
Classifier: Framework :: Bob
Classifier: Development Status :: 4 - Beta
Classifier: Environment :: Console
Classifier: Intended Audience :: Developers
Classifier: Intended Audience :: Education
Classifier: Intended Audience :: Science/Research
Classifier: License :: OSI Approved :: BSD License
Classifier: Natural Language :: English
Classifier: Programming Language :: Python
Classifier: Programming Language :: Python :: 3
Classifier: Topic :: Scientific/Engineering :: Artificial Intelligence
Classifier: Topic :: Database :: Front-Ends
